sysbus/__init__.py
sysbus/manuf
sysbus/manuf.py
sysbus/sysbus.py
sysbus-1.0.9.dist-info/LICENSE
sysbus-1.0.9.dist-info/METADATA
sysbus-1.0.9.dist-info/WHEEL
sysbus-1.0.9.dist-info/entry_points.txt
sysbus-1.0.9.dist-info/top_level.txt
sysbus-1.0.9.dist-info/RECORD
