Metadata-Version: 2.1
Name: sysbus
Version: 1.0.9
Summary: Control by script your Livebox 2,3,4
Home-page: https://rene-d.github.io/sysbus
Author: Rene Devichi
Author-email: rene.github@gmail.com
License: UNKNOWN
Project-URL: Source, https://github.com/rene-d/sysbus
Project-URL: Bug Reports, https://github.com/rene-d/sysbus/issues
Keywords: livebox sysbus
Platform: UNKNOWN
Classifier: License :: OSI Approved :: MIT License
Classifier: Development Status :: 5 - Production/Stable
Classifier: Operating System :: OS Independent
Classifier: Programming Language :: Python :: 3 :: Only
Classifier: Programming Language :: Python :: 3.5
Classifier: Programming Language :: Python :: 3.6
Classifier: Programming Language :: Python :: 3.7
Classifier: Programming Language :: Python :: 3.8
Classifier: Environment :: Console
Classifier: Topic :: Home Automation
Classifier: Intended Audience :: Telecommunications Industry
Classifier: Intended Audience :: Science/Research
Requires-Python: >=3.5
Requires-Dist: requests
Requires-Dist: graphviz
Requires-Dist: qrcode
Requires-Dist: python-dateutil
